{"code": 0, "data": {"allow_search": true, "attention": false, "author_title": null, "blocked": false, "blocked_count": null, "can_del": false, "comments": [{"author_title": "", "blocked": false, "blocked_count": 0, "can_del": false, "cid": -1, "create_time": 1650986560, "is_blocked": false, "is_tmp": false, "name_id": 1, "text": "我也不会", "timestamp": 1650986560}, {"author_title": "", "blocked": true, "blocked_count": 0, "can_del": false, "cid": -1, "create_time": 1650986642, "is_blocked": false, "is_tmp": false, "name_id": 2, "text": "", "timestamp": 1650986642}, {"author_title": "", "blocked": false, "blocked_count": 0, "can_del": false, "cid": -1, "create_time": 1650986642, "is_blocked": false, "is_tmp": false, "name_id": 2, "text": "如何评价博士生找不到回车键", "timestamp": 1650986642}, {"author_title": "", "blocked": false, "blocked_count": 0, "can_del": false, "cid": -1, "create_time": 1650987411, "is_blocked": false, "is_tmp": false, "name_id": 3, "text": "Re Bob: 一键部署，一键指挥", "timestamp": 1650987411}, {"author_title": "", "blocked": false, "blocked_count": 0, "can_del": false, "cid": -1, "create_time": 1650991764, "is_blocked": false, "is_tmp": false, "name_id": 4, "text": "Re Bob: 触摸谁呢", "timestamp": 1650991764}], "create_time": 1650985426, "cw": null, "hot_score": null, "is_blocked": false, "is_reported": null, "is_tmp": false, "last_comment_time": 1650991764, "likenum": 1, "n_attentions": 1, "n_comments": 5, "pid": 32182, "poll": null, "reply": 0, "text": "存在的从来不是爱而是欲，“爱情”就是短时间的荷尔蒙爆发和之后长时间的荷尔蒙受抑低迷", "timestamp": 1650985426}}