{
    "252": {
        "0c63fe56775150893c2842069b8fd23_720w.png": "dir1"
    },
    "1098": {
        "tiwUzNuAG2ehxso.jpg": "dir2"
    },
    "1212": {
        "nt7hODBVcIFjZuw.jpg": "dir2"
    },
    "1353": {
        "o1h4OAsmukxrlZR.jpg": "dir2"
    },
    "1438": {
        "4d61b2fe2.png@942w_1221h_progressive.png": "dir1",
        "CZJnjvTwih5FRau.jpg": "dir2"
    },
    "1686": {
        "gprc4mfwR7osnTQ.jpg": "dir1",
        "ko37iwXN2yc9Qpd.jpg": "dir1",
        "wIGhOX14iJYSFvU.jpg": "dir1",
        "x3gL4PznNrVXQAa.jpg": "dir1",
        "XtZrIOh1zkVpnvu.jpg": "dir1"
    },
    "1712": {
        "G1eLKzmpcWE8hVF.png": "dir2"
    },
    "1803": {
        "tu3oM84T7L2EGvW.jpg": "dir2"
    },
    "1826": {
        "cRvFmVJsiSqPpUZ.jpg": "dir1"
    },
    "1893": {
        "v5MncoOZyAeKlgh.jpg": "dir1"
    },
    "2702": {
        "2-f03d0a82beb813d948aa3d5dd18e0731_r.jpg": "dir1"
    },
    "2819": {
        "3R8va2WqemUkTzF.jpg": "dir1",
        "EkSxBFo9Cy4sTuh.jpg": "dir1",
        "G5BDk4szMJ1i97W.jpg": "dir1",
        "gWs2HbnrzG65hwM.jpg": "dir1",
        "SUKWR3aj2x6XkzN.jpg": "dir1",
        "XNskFTKnZOebM5B.jpg": "dir1",
        "YJbvfANRlwK8Lp2.jpg": "dir1"
    },
    "3059": {
        "KkgEUvJCbjtOei7.jpg": "dir2",
        "lVSAQ5WJx7RYZG4.jpg": "dir1"
    },
    "3152": {
        "WzZEYyAwTb8XGHn.jpg": "dir1"
    },
    "3163": {
        "puAb3YVMSiktxNc.jpg": "dir1"
    },
    "3219": {
        "4rTFwmuxqZKjJhc.jpg": "dir1"
    },
    "3310": {
        "fOuDZkAJiF8YqmE.jpg": "dir1"
    },
    "3311": {
        "wBV1ljNGsR894tS.jpg": "dir1"
    },
    "3351": {
        "OCeBAXtwFarN43K.jpg": "dir1"
    },
    "3434": {
        "KjTMnkHiLqIWFCy.jpg": "dir1"
    },
    "3439": {
        "hjuAJna93cYdSps.png": "dir1"
    },
    "3529": {
        "8HOrFixgPfQBzG2.jpg": "dir1",
        "9EHaMnxz4YWBPS3.jpg": "dir1",
        "eV5l4kETqhNspg3.jpg": "dir1"
    },
    "3546": {
        "DwbgQ71nR9ra5Ep.jpg": "dir1"
    },
    "3557": {
        "h4h3nn.jpg": "dir1"
    },
    "3605": {
        "OztxbhunP4vqo13.jpg": "dir1"
    },
    "3650": {
        "jv8pxf.jpg": "dir1"
    },
    "3669": {
        "PXeEF1kbIMZrUOi.png": "dir1"
    },
    "3677": {
        "sl1r42.jpg": "dir1"
    },
    "3702": {
        "QZIvPms9L6qHXSD.jpg": "dir1"
    },
    "3719": {
        "weNljY9mrxbVHMi.jpg": "dir1",
        "ye3bLpUdXB9Ofkq.jpg": "dir1"
    },
    "3722": {
        "jv74ef.jpg": "dir1"
    },
    "3757": {
        "jv7u8j.jpg": "dir1"
    },
    "3784": {
        "jv7vrw.jpg": "dir1"
    },
    "3820": {
        "jv88hy.jpg": "dir1"
    },
    "3853": {
        "jv8enq.jpg": "dir1"
    },
    "3877": {
        "5ioan0x.jpg": "dir1"
    },
    "3899": {
        "jv9ktb.jpg": "dir1"
    },
    "3923": {
        "jv8y62.jpg": "dir1"
    },
    "3945": {
        "slmaop.jpg": "dir1"
    },
    "3959": {
        "idn4u4.jpg": "dir1"
    },
    "3979": {
        "KaqJeocn5iVCT2l.png": "dir1"
    },
    "3984": {
        "tYBmHTREbskFJ4c.jpg": "dir1"
    },
    "3985": {
        "jv9xul.jpg": "dir1"
    },
    "4021": {
        "lj9z41.jpg": "dir1"
    },
    "4039": {
        "mdohv9.jpg": "dir1"
    },
    "4050": {
        "ektbnPS5L4A1fB6.png": "dir1"
    },
    "4069": {
        "mdlgdq.jpg": "dir1"
    },
    "4093": {
        "tBW9OZT2blo4QD1.png": "dir1"
    },
    "4110": {
        "ljbg0p.jpg": "dir1"
    },
    "4133": {
        "md0xfb.jpg": "dir1"
    },
    "4164": {
        "lj9znu.jpg": "dir1"
    },
    "4185": {
        "y7IlaUxef1KoAMY.jpg": "dir1"
    },
    "4190": {
        "jv92q7.jpg": "dir1"
    },
    "4206": {
        "5Fb826DCHITwgW9.jpg": "dir1"
    },
    "4217": {
        "kt9arp.jpg": "dir1"
    },
    "4259": {
        "md39ty.jpg": "dir1"
    },
    "4284": {
        "ljbcwz.jpg": "dir1"
    },
    "4322": {
        "gBzlQoyPt7kDqCe.jpg": "dir1"
    },
    "4339": {
        "6SKdORWEzxBTcCi.jpg": "dir1"
    },
    "4366": {
        "mdlqh5.jpg": "dir1"
    },
    "4380": {
        "ljblsy.jpg": "dir1"
    },
    "4411": {
        "jv98lt.jpg": "dir1"
    },
    "4422": {
        "ljangm.jpg": "dir1"
    },
    "4440": {
        "md6llz.jpg": "dir1"
    },
    "4458": {
        "lj9xq5.jpg": "dir1"
    },
    "4490": {
        "jv9m2r.jpg": "dir1"
    },
    "4505": {
        "2wo1cv9ThQqPxAs.jpg": "dir1"
    },
    "4509": {
        "96SypXWz8vcONlP.jpg": "dir1"
    },
    "4535": {
        "mdoazo.jpg": "dir1"
    },
    "4550": {
        "lbdK687ueSFBcwJ.jpg": "dir1"
    },
    "4561": {
        "riRNuLECzwd8VUh.jpg": "dir1"
    },
    "4567": {
        "2zhasdfOHCS3b6X.png": "dir1"
    },
    "4602": {
        "10twx4n.jpg": "dir1"
    },
    "4613": {
        "SPV7DCUHwYaTLOq.png": "dir1",
        "uE9SNHiyKAIJYxQ.png": "dir1",
        "xScpYK42zm3G1kf.png": "dir1"
    },
    "4617": {
        "gM549NCsxcHWFDP.png": "dir1"
    },
    "4632": {
        "md3u1y.jpg": "dir1"
    },
    "4637": {
        "natdSJU7OQLGvhg.jpg": "dir1",
        "x1KauskLgAGmYw4.jpg": "dir1"
    },
    "4648": {
        "236pov.jpg": "dir1"
    },
    "4706": {
        "27vxxf.jpg": "dir1"
    },
    "4718": {
        "ljamg5.jpg": "dir1",
        "lsz3r5.png": "dir1"
    },
    "4724": {
        "zFCUcNZXtARKmkT.jpg": "dir1"
    },
    "4742": {
        "247qnr.jpg": "dir1"
    },
    "4763": {
        "ljbvuv.jpg": "dir1"
    },
    "4778": {
        "4bGpOVt29xBvfns.jpg": "dir1"
    },
    "4788": {
        "21cv3a.jpg": "dir1"
    },
    "4796": {
        "1AMvwpZ3uRIOKfl.jpg": "dir1",
        "bweKVkDQSNT6RgG.jpg": "dir1",
        "o1cPBDilaE9S3eH.jpg": "dir1",
        "TMEYpjXaDOdvrZ6.jpg": "dir1",
        "vmY9QJHq4GXFcru.jpg": "dir1"
    },
    "4809": {
        "29rnw7.jpg": "dir1"
    },
    "4829": {
        "sln5g7.jpg": "dir1"
    },
    "4831": {
        "P4ouBvGYUjiMDac.jpg": "dir1"
    },
    "4860": {
        "22klk7.jpg": "dir1"
    },
    "4879": {
        "6tv7WTrkfIuNjQE.jpg": "dir1",
        "DfBJF3NQtWksZq9.jpg": "dir1",
        "LmwMtYsEey5hQrZ.jpg": "dir1"
    },
    "4882": {
        "28jan2.jpg": "dir1"
    },
    "4885": {
        "r6h9WYR3iEZacAx.jpg": "dir1"
    },
    "4941": {
        "29qan4.jpg": "dir1"
    },
    "4955": {
        "pKZcxdoNtilHRFb.png": "dir1"
    },
    "4998": {
        "ljbq69.jpg": "dir1"
    },
    "4999": {
        "jv9g8a.jpg": "dir1"
    },
    "5030": {
        "3dt7ts.jpg": "dir1"
    },
    "5063": {
        "hAmn7ty5c3BqgG4.jpg": "dir1",
        "qaAcH5XLQ9notb8.jpg": "dir1"
    },
    "5079": {
        "23yw7h.jpg": "dir1"
    },
    "5092": {
        "27whxf.jpg": "dir1"
    },
    "5106": {
        "10txhjy.jpg": "dir1"
    },
    "5126": {
        "jv9gj2.jpg": "dir1"
    },
    "5192": {
        "ba5QOqcphsDyAKE.jpg": "dir1"
    },
    "5203": {
        "D4HzJ2MqmY6ZCrA.png": "dir1"
    },
    "5206": {
        "mdl5kb.jpg": "dir1"
    },
    "5224": {
        "AUfSiHL7jp9Mu5Z.png": "dir1",
        "MlgWPkJuOHLsoBx.png": "dir1"
    },
    "5293": {
        "lja28k.jpg": "dir1"
    },
    "5330": {
        "hzOAknaoJPIt248.jpg": "dir1"
    },
    "5518": {
        "md3we7.jpg": "dir1"
    },
    "5571": {
        "ot6059.jpg": "dir1"
    },
    "5576": {
        "7a61766992a283dc.jpeg": "dir1"
    },
    "5767": {
        "23xt19.jpg": "dir1"
    },
    "5787": {
        "10txnwj.jpg": "dir1",
        "23xt19.jpg": "dir1",
        "281r2p.jpg": "dir1",
        "67n6wan.jpg": "dir1",
        "lja28k.jpg": "dir1",
        "ljaro8.jpg": "dir1",
        "ljbrx4.jpg": "dir1",
        "md3gv4.jpg": "dir1",
        "md3we7.jpg": "dir1",
        "mdlvwv.jpg": "dir1",
        "xr82ox.jpg": "dir1"
    },
    "5845": {
        "57mZMto3azCqe8V.jpg": "dir1"
    },
    "5893": {
        "iONZVDoxYaGQ9Td.jpg": "dir1"
    },
    "5896": {
        "vFh6UPYi8ypkaVl.jpg": "dir1"
    },
    "5955": {
        "O5Z4lnRKNeiuY2t.jpg": "dir1"
    },
    "5960": {
        "9swTQvLyKB2eYGd.jpg": "dir1"
    },
    "6026": {
        "j1ZlukIg5BeSmGT.jpg": "dir1"
    },
    "6033": {
        "X4mSzC5wYAhxGsI.jpg": "dir1"
    },
    "6088": {
        "blKHPQo7h5TwEWV.jpg": "dir1"
    },
    "6095": {
        "rcblkr.jpg": "dir1"
    },
    "6107": {
        "rdkdgs.jpg": "dir1"
    },
    "6117": {
        "rd0a2m.jpg": "dir1"
    },
    "6129": {
        "DUfkO2p3WCqHy5w.jpg": "dir1"
    },
    "6135": {
        "rb91sq.jpg": "dir1"
    },
    "6139": {
        "IAOxpgblCyQeY9N.jpg": "dir1"
    },
    "6143": {
        "EpRau5VLUMmb2d1.jpg": "dir1"
    },
    "6146": {
        "1259ijg.jpg": "dir1"
    },
    "6161": {
        "ginal%20raika_%28rry_raika%29%20tree.jpg": "dir2"
    },
    "6170": {
        "5Qmil72JgShEt9M.jpg": "dir1",
        "DZFvwAdQxPn5zjX.jpg": "dir1",
        "rvFjGPimYpzXucB.jpg": "dir1"
    },
    "6180": {
        "cnx8SeauIqtwimT.jpg": "dir1"
    },
    "6181": {
        "QfSVmc7bO34lAaX.jpg": "dir1"
    },
    "6184": {
        "RhF7CZOvy9Dcm81.png": "dir1"
    },
    "6194": {
        "ESwjqpaAuUDTOmV.jpg": "dir1",
        "WDUTXAGtdOP9iLz.jpg": "dir1",
        "YBZnCFL5X7ytSuk.jpg": "dir1"
    },
    "6195": {
        "hvL6fwqAi4KTBro.png": "dir1"
    },
    "6208": {
        "RITtyXW3JHkBesA.png": "dir1"
    },
    "6220": {
        "alwv29n.jpg": "dir1"
    },
    "6230": {
        "126bu6g.jpg": "dir1"
    },
    "6236": {
        "rba3gr.jpg": "dir1"
    },
    "6238": {
        "X1hFcRgVDyO8x6Y.jpg": "dir1"
    },
    "6244": {
        "rdkva2.jpg": "dir1"
    },
    "6249": {
        "i4wgQHbD1ICaBrE.jpg": "dir1"
    },
    "6254": {
        "KXurphM7mIU4WBL.jpg": "dir1"
    },
    "6266": {
        "NhV26kSyeUDBl8b.jpg": "dir1"
    },
    "6279": {
        "3diptx.jpg": "dir1"
    },
    "6291": {
        "LOyhBsZGnwqXd35.jpg": "dir1",
        "q8GZFp7Wtwr2mVE.jpg": "dir1"
    },
    "6296": {
        "rbaek9.jpg": "dir1"
    },
    "6303": {
        "rbn619.jpg": "dir1"
    },
    "6316": {
        "281r2p.jpg": "dir1"
    },
    "6369": {
        "10txnwj.jpg": "dir1",
        "10txyct.jpg": "dir1"
    },
    "6377": {
        "3dt1g7.jpg": "dir1"
    },
    "6392": {
        "9ZqDapdleCtgTf8.png": "dir1"
    },
    "6401": {
        "126vnw6.jpg": "dir1"
    },
    "6411": {
        "Of1co4MVkyTNSGW.jpg": "dir1"
    },
    "6416": {
        "klmOWQ2j9VxRCPo.jpg": "dir1"
    },
    "6419": {
        "vPy1zDC9OAV2iRc.png": "dir1"
    },
    "6425": {
        "ljaa1p.jpg": "dir1"
    },
    "6431": {
        "Ylm7gDKyM2EsLnS.jpg": "dir1"
    },
    "6438": {
        "p7BrMC19cX6Dwv4.png": "dir1"
    },
    "6440": {
        "rbnx9k.jpg": "dir1"
    },
    "6444": {
        "253X7xqp96Glgmk.jpg": "dir1"
    },
    "6458": {
        "rdl4hh.jpg": "dir1"
    },
    "6497": {
        "RxeK5CpHMg1z6US.jpg": "dir2"
    },
    "6498": {
        "KOcYMw1iNaUkCIe.jpg": "dir2"
    },
    "6502": {
        "rb99c1.jpg": "dir1"
    },
    "6512": {
        "rbpd27.jpg": "dir1"
    },
    "6538": {
        "125syi5.jpg": "dir1"
    },
    "6547": {
        "haIVLBkQ2eyHu8Y.jpg": "dir1"
    },
    "6553": {
        "ljafwh.jpg": "dir1"
    },
    "6567": {
        "rdl9nm.jpg": "dir1"
    },
    "6599": {
        "aMIV8bzhBD7oZRH.jpg": "dir1",
        "jRn8E4kt35phDCq.jpg": "dir1",
        "yZM3kdeC7upT5a4.jpg": "dir1"
    },
    "6612": {
        "t5WCHDYkgNUMuzE.jpg": "dir2"
    },
    "6613": {
        "IyLWfgVFQbX84Ai.jpg": "dir1"
    },
    "6614": {
        "uV26YB4OaEhDFUA.jpg": "dir1"
    },
    "6615": {
        "kc8gSzapFQKh3JV.jpg": "dir1"
    },
    "6624": {
        "ptJjuyV3r2P9WIL.png": "dir1"
    },
    "6684": {
        "MldyC7oUbhw82sQ.jpg": "dir1"
    },
    "6691": {
        "3VMzO4YPjNS159n.jpg": "dir1",
        "iKSRgVWuClbIBXM.jpg": "dir1",
        "M4XfWEl1BmTebYZ.jpg": "dir1",
        "Ms2PcgYACju5nxV.jpg": "dir1",
        "VhIDjb5UTr9cSkf.jpg": "dir1"
    },
    "6709": {
        "126vdrk.jpg": "dir1"
    },
    "6723": {
        "w1b985.jpg": "dir1"
    },
    "6726": {
        "Xcw8RkeG1ros4nI.png": "dir1"
    },
    "6727": {
        "sf6zd0.jpg": "dir1"
    },
    "6734": {
        "sM4zYmikT3vebLU.png": "dir1"
    },
    "6740": {
        "rbpmse.jpg": "dir1"
    },
    "6753": {
        "wd5jm8.jpg": "dir1"
    },
    "6783": {
        "YHyUCkuLnevKgoi.png": "dir1"
    },
    "6784": {
        "EuvT4BDC26rtna5.png": "dir1"
    },
    "6799": {
        "Ray6dY7Lhs9JOw2.png": "dir1"
    },
    "6800": {
        "QWfRt7VUI82ewqS.jpg": "dir1"
    },
    "6812": {
        "rd0l8a.jpg": "dir1"
    },
    "6813": {
        "10txecy.jpg": "dir1",
        "22k4ww.jpg": "dir1",
        "22klk7.jpg": "dir1",
        "23yw7h.jpg": "dir1",
        "27ewb4.jpg": "dir1",
        "5ioan0x.jpg": "dir1",
        "idn4u4.jpg": "dir1",
        "jv74ef.jpg": "dir1",
        "jv7u8j.jpg": "dir1",
        "jv7vrw.jpg": "dir1",
        "jv88hy.jpg": "dir1",
        "jv8enq.jpg": "dir1",
        "jv8y62.jpg": "dir1",
        "jv9ktb.jpg": "dir1",
        "jv9xul.jpg": "dir1",
        "lj9z41.jpg": "dir1",
        "slmaop.jpg": "dir1"
    },
    "6820": {
        "126bzr3.jpg": "dir1"
    },
    "6824": {
        "fGw6CH5aYSAWpy4.jpg": "dir1"
    },
    "6827": {
        "w5kudp.jpg": "dir1"
    },
    "6828": {
        "GEPLi7JXhdmVOnA.jpg": "dir1"
    },
    "6835": {
        "rdkarc.jpg": "dir1"
    },
    "6844": {
        "125lqnh.jpg": "dir1"
    },
    "6861": {
        "T6hPE7oK5uLX4Dl.jpg": "dir1"
    },
    "6875": {
        "rd3bix.jpg": "dir1"
    },
    "6881": {
        "ple_eyes%20sannio%20tail%20watermark.jpg": "dir1"
    },
    "6883": {
        "w1whud.jpg": "dir1"
    },
    "6909": {
        "rbq7o6.jpg": "dir1"
    },
    "6915": {
        "1xpi58.jpg": "dir1"
    },
    "6932": {
        "BeM7dj4LtGSvE1Y.jpg": "dir1"
    },
    "6933": {
        "3dj3rl.jpg": "dir1",
        "md6llz.jpg": "dir1",
        "xr82ox.jpg": "dir1"
    },
    "6938": {
        "ple_eyes%20sannio%20tail%20watermark.jpg": "dir1"
    },
    "6955": {
        "wc5zoi.jpg": "dir1"
    },
    "6959": {
        "HABTnl283GUov1i.jpg": "dir1"
    },
    "6960": {
        "k5vItx9sDJ6n7Em.jpg": "dir1"
    },
    "6973": {
        "BGzEX2bo9tqdajx.jpg": "dir1"
    },
    "6990": {
        "OqFTbiK5HyrNLXn.jpg": "dir1"
    },
    "7034": {
        "w045av.jpg": "dir1"
    },
    "7037": {
        "BTuoeOxwXbc3U1i.png": "dir1",
        "NUpn7lBA1xW2OVz.png": "dir1",
        "TbMEYKIo6uXqGa3.png": "dir1"
    },
    "7067": {
        "89JkmwZPbXdRGqy.jpg": "dir1"
    },
    "7072": {
        "f9doHMVy25krQ3T.jpg": "dir1"
    },
    "7084": {
        "wcmv2q.jpg": "dir1"
    },
    "7089": {
        "20unxb.jpg": "dir1"
    },
    "7100": {
        "126d4if.jpg": "dir1"
    },
    "7133": {
        "21izgz.jpg": "dir1"
    },
    "7140": {
        "G4YHaFCAg2ctvVB.jpg": "dir1"
    },
    "7141": {
        "rcy45d.jpg": "dir1"
    },
    "7151": {
        "126c426.jpg": "dir1"
    },
    "7186": {
        "1Y6fZNPoJXEvFpO.jpg": "dir1"
    },
    "7198": {
        "1y9wnz.jpg": "dir1"
    },
    "7199": {
        "O684UtkuxdnRYFN.jpg": "dir1"
    },
    "7214": {
        "4Enylhwa2HrIZbM.png": "dir1"
    },
    "7218": {
        "w1bzym.jpg": "dir1"
    },
    "7239": {
        "rcbfv9.jpg": "dir1"
    },
    "7267": {
        "rcgqi1.jpg": "dir1"
    },
    "7280": {
        "ulAMESKQkHG36cp.jpg": "dir1"
    },
    "7285": {
        "1.2.jpg": "dir2"
    },
    "7294": {
        "gjZtLSI9oDJCNr5.jpg": "dir1",
        "RfPSNzHUE9g5qdk.jpg": "dir1"
    },
    "7324": {
        "9uJkfY84HUvCwFV.jpg": "dir1"
    },
    "7335": {
        "rbqlbt.jpg": "dir1"
    },
    "7358": {
        "5mid2bz.jpg": "dir1"
    },
    "7362": {
        "LFurHYGCzTBfJw5.jpg": "dir1"
    },
    "7382": {
        "iB89FgmXPpkYoZS.jpg": "dir1"
    },
    "7385": {
        "Yl5LBHMqNkPz3eW.jpg": "dir1"
    },
    "7417": {
        "AzWYCk2OTU1BEKF.jpg": "dir1"
    },
    "7427": {
        "VSJWz1xM6y5lCw7.jpg": "dir1"
    },
    "7428": {
        "xHSdcY7fW6JbZO9.png": "dir1"
    },
    "7448": {
        "24x4m9.jpg": "dir1"
    },
    "7467": {
        "VW4qT8UEBrxhaG1.jpg": "dir1"
    },
    "7536": {
        "5s2z31.jpg": "dir1"
    },
    "7590": {
        "rccnij.jpg": "dir1"
    },
    "7596": {
        "Ssi7MpLrjECPg2B.jpg": "dir1"
    },
    "7600": {
        "ReJ4YchTGbfdigP.jpg": "dir1"
    },
    "7607": {
        "o4OhuGLYT3Qz2RS.png": "dir1"
    },
    "7610": {
        "du7EcbFtN6emMP3.jpg": "dir1"
    },
    "7612": {
        "RxeHQ634ViUypnv.jpg": "dir1"
    },
    "7614": {
        "fpV2jZWwzt3uNrM.jpg": "dir1"
    },
    "7630": {
        "3dqkg6.jpg": "dir1"
    },
    "7653": {
        "125sqo5.jpg": "dir1"
    },
    "7662": {
        "gozYJjKvbpBTVuk.jpg": "dir1"
    },
    "7665": {
        "rd3p8r.jpg": "dir1"
    },
    "7680": {
        "AKO3582cyDBFIXP.jpg": "dir1"
    },
    "7681": {
        "5420521.jpg": "dir1"
    },
    "7684": {
        "cMNsQ14XoAqlGZw.jpg": "dir1"
    },
    "7690": {
        "AaB8CmqdxyOF6vn.jpg": "dir1",
        "kTYeEI5ah873gFZ.jpg": "dir1",
        "tjYfvDL4EpwFAqK.jpg": "dir1",
        "XQTV4SGfwEhbUZd.jpg": "dir1"
    },
    "7701": {
        "gaU4hcsz2eDIVNj.jpg": "dir1"
    },
    "7743": {
        "k9jgj7.jpg": "dir1"
    },
    "7762": {
        "T6HkGBLdMl7pVQF.jpg": "dir1"
    },
    "7786": {
        "XTRZIanEAQqw6eh.jpg": "dir1"
    },
    "7789": {
        "nOW8CfTZtQ6ABHj.png": "dir1"
    },
    "7805": {
        "8b259fb7c2da92de.jpg": "dir1"
    },
    "7813": {
        "hq5Gd6OrXAb7sLY.jpg": "dir1"
    },
    "7869": {
        "396HAsGfRFrpXPD.jpg": "dir1"
    },
    "7871": {
        "aGSiP81xcYBKmTU.jpg": "dir1"
    },
    "7874": {
        "guAZbUhmIpMTldz.jpg": "dir1"
    },
    "7886": {
        "rd1avtKx7cDWLYO.jpg": "dir1"
    },
    "7897": {
        "3DfRX85ZWxvC2Yt.png": "dir1"
    },
    "7901": {
        "wcahmu.jpg": "dir1"
    },
    "7918": {
        "UzfkJZO5cjYRxMK.jpg": "dir1"
    },
    "7933": {
        "4hd2lL6bfimDEW5.png": "dir1"
    },
    "7937": {
        "FUjR2oiHvs1BY5Z.jpg": "dir1"
    },
    "7981": {
        "hf2k75m8lZHtcPE.jpg": "dir1"
    },
    "8004": {
        "1OWqHZxltvTeBRQ.png": "dir1",
        "ghp98KOVPiYU3Wk.png": "dir1",
        "HWbeV5aSMDIX8xl.png": "dir1",
        "lvdxyDLQCUj65ho.png": "dir1"
    },
    "8012": {
        "9vex612VSPuQFCM.jpg": "dir1"
    },
    "8023": {
        "tYk8eKEJwqFfCDW.jpg": "dir1"
    },
    "8048": {
        "xHflbg5wYX6hVA7.jpg": "dir1"
    },
    "8064": {
        "U6451xoTn9PKIAr.jpg": "dir1"
    },
    "8089": {
        "1JX3crasjA5uW2H.jpg": "dir1"
    },
    "8096": {
        "HFnQsUgBTzoEdMt.png": "dir1"
    },
    "8102": {
        "ypd6FTDKYhWsmCO.jpg": "dir1"
    },
    "8104": {
        "QdEFPbKVytGI17R.jpg": "dir1"
    },
    "8110": {
        "vEir3OAR9uLcNQs.png": "dir1"
    },
    "8115": {
        "1xwelc.jpg": "dir1"
    },
    "8119": {
        "Zj36vcXBk9Vx4Ad.jpg": "dir1"
    },
    "8130": {
        "3dgpg3.jpg": "dir1"
    },
    "8137": {
        "zkK2w6qvD5ISFTt.jpg": "dir1"
    },
    "8149": {
        "125lk6b.jpg": "dir1"
    },
    "8152": {
        "zV9MbcqPUjgekar.jpg": "dir1"
    },
    "8178": {
        "wcsslp.jpg": "dir1"
    },
    "8188": {
        "eazk7TO5rWpKSwL.jpg": "dir1"
    },
    "8214": {
        "wQD1utpRb2nihCv.png": "dir1"
    },
    "8219": {
        "ySOvWJu1hjDY8dE.jpg": "dir1"
    },
    "8221": {
        "wd5IPtJab2HrO7Y.jpg": "dir1"
    },
    "8225": {
        "XtGo6C3YpJZgABa.jpg": "dir1"
    },
    "8234": {
        "rcg268.jpg": "dir1"
    },
    "8252": {
        "k9m7te.jpg": "dir1"
    },
    "8287": {
        "rdcp98.jpg": "dir1"
    },
    "8288": {
        "cXmPEtMaj2VbgLI.png": "dir1"
    },
    "8291": {
        "HgeNQbt1PLxvG64.jpg": "dir1",
        "HyiMmwhp341SFL9.jpg": "dir1",
        "X1C49G8gDKFLMdx.jpg": "dir1",
        "zKA3rfNvZPkXoSB.jpg": "dir1"
    },
    "8298": {
        "1yc4vo.jpg": "dir1"
    },
    "8313": {
        "DN5z4nFG8iroKyg.jpg": "dir1"
    },
    "8325": {
        "cHTzh3F5GYdt8Kk.jpg": "dir1"
    },
    "8341": {
        "M5gvQeTX9tPhNpf.jpg": "dir1"
    },
    "8347": {
        "rwtnmuIsRFviQTq.jpg": "dir1"
    },
    "8351": {
        "mhGBOxoRYDVQbXH.jpg": "dir1"
    },
    "8359": {
        "rZCuf9OsiVjd4X3.png": "dir1"
    },
    "8380": {
        "iL4JgQyqjASIKMY.jpg": "dir1"
    },
    "8381": {
        "k9gewm.jpg": "dir1"
    },
    "8395": {
        "rbufzu.jpg": "dir1"
    },
    "8397": {
        "asWBxO3InlNvTQE.jpg": "dir1"
    },
    "8427": {
        "ZyBpmlx8bHWPdhI.jpg": "dir1"
    },
    "8442": {
        "w050zj.jpg": "dir1"
    },
    "8461": {
        "MyXkwBZDEAx9r7C.png": "dir1"
    },
    "8478": {
        "lq1wv3.jpg": "dir1"
    },
    "8492": {
        "bSfrD4tI5gyKCmj.jpg": "dir1"
    },
    "8513": {
        "1xbog8.jpg": "dir1"
    },
    "8546": {
        "218xl3.jpg": "dir1"
    },
    "8554": {
        "hWDNZM16RfPXvym.png": "dir1"
    },
    "8562": {
        "lqemao.jpg": "dir1"
    },
    "8572": {
        "lqjc3o.jpg": "dir1"
    },
    "8587": {
        "z9VirAeN7wkcUBo.png": "dir1"
    },
    "8598": {
        "lqc54j.jpg": "dir1",
        "md3gv4.jpg": "dir1"
    },
    "8607": {
        "TcHpBUZE1N8qIAM.jpg": "dir1"
    },
    "8626": {
        "w4umte.jpg": "dir2"
    },
    "8645": {
        "bkiMPsE2lUY1L8z.jpg": "dir1"
    },
    "8658": {
        "sf6kxr.jpg": "dir1"
    },
    "8664": {
        "k9jjdm.jpg": "dir1"
    },
    "8671": {
        "126c5fv.jpg": "dir1"
    },
    "8689": {
        "wdczpn.jpg": "dir1"
    },
    "8709": {
        "lqh7gw.jpg": "dir1"
    },
    "8718": {
        "E4nGdomBsD9N5tb.png": "dir1"
    },
    "8726": {
        "Ef287NOagzjM3WS.jpg": "dir1"
    },
    "8727": {
        "rdorj5.jpg": "dir1"
    },
    "8728": {
        "YVuhQKsUitj87oF.jpg": "dir2"
    },
    "8748": {
        "JFUc7HbGSxLCDWg.jpg": "dir1"
    },
    "8788": {
        "lqm8u8.jpg": "dir1"
    },
    "8795": {
        "60nvtul.jpg": "dir1"
    },
    "8806": {
        "sipH2KRdzLgFXCE.jpg": "dir1"
    },
    "8807": {
        "qv3wsQJ4hIMzXY1.png": "dir1"
    },
    "8810": {
        "1xdl0e.jpg": "dir1"
    },
    "8817": {
        "rcdijr.jpg": "dir1"
    },
    "8848": {
        "lnhios.jpg": "dir1"
    },
    "8858": {
        "md3gv4.jpg": "dir1"
    },
    "8864": {
        "125sh8k.jpg": "dir1"
    },
    "8910": {
        "46f6c7cadaebfad8c11c67760e77c7_1440w.png": "dir1"
    },
    "8920": {
        "w4tliu.jpg": "dir1"
    },
    "8933": {
        "3dm3bz.jpg": "dir1"
    },
    "8939": {
        "k9czju.jpg": "dir1"
    },
    "8979": {
        "w5hws2.jpg": "dir2"
    },
    "9042": {
        "OWJiE3mpf21FYxU.jpg": "dir1"
    },
    "9058": {
        "MpfODQg8h3KEsYC.jpg": "dir1"
    },
    "9059": {
        "119i81s.jpg": "dir1"
    },
    "9065": {
        "k1Z7lpN5dxeJiVm.jpg": "dir1"
    },
    "9081": {
        "k9nvk2.jpg": "dir1"
    },
    "9116": {
        "1227b1y.jpg": "dir2"
    },
    "9172": {
        "125kzcc.jpg": "dir1"
    },
    "9205": {
        "5JYGkxL8XtMfeW4.jpg": "dir1"
    },
    "9208": {
        "ouFqPSCkhlwv4Zf.jpg": "dir1"
    },
    "9214": {
        "BSFOLV2c5XM4AlT.jpg": "dir1"
    },
    "9230": {
        "fLWP2RbxyhJTu8X.jpg": "dir1"
    },
    "9239": {
        "ldtHwp3eDZbaVE2.jpg": "dir1"
    },
    "9243": {
        "xAQICMYgXsJPKi6.png": "dir1"
    },
    "9250": {
        "z9uLG3wTg1PiBcS.jpg": "dir1"
    },
    "9312": {
        "MjFx8oGUhRfdC9E.jpg": "dir1"
    },
    "9336": {
        "UnlDLHruhKNf54j.jpg": "dir1"
    },
    "9374": {
        "lr19gj.jpg": "dir1",
        "mdlvwv.jpg": "dir1"
    },
    "9505": {
        "125ks9c.jpg": "dir1"
    },
    "9561": {
        "YfpNXtVxjElJTsn.jpg": "dir2"
    },
    "9640": {
        "uX9NdpOni3VvFbK.jpg": "dir1"
    },
    "9643": {
        "lqi605.jpg": "dir1"
    },
    "9655": {
        "OWlj9Sh83edpswX.png": "dir1"
    },
    "9681": {
        "KgFTlACkORaxyp8.png": "dir1"
    },
    "9741": {
        "ChdrJeFa9wzPqSA.jpg": "dir1"
    },
    "9889": {
        "8nosArci71d2uWG.jpg": "dir1"
    },
    "9905": {
        "WnjVdqhLtI367Jb.png": "dir1"
    },
    "9911": {
        "Z6fNYpWA9ybJPxo.jpg": "dir1"
    },
    "9928": {
        "lpg0hj.jpg": "dir1"
    },
    "9937": {
        "2MGw8pFJ9ubYLCO.jpg": "dir1"
    },
    "9944": {
        "GNF19p72UrVM3Cq.png": "dir1"
    },
    "9967": {
        "lq2xvd.jpg": "dir1"
    },
    "10011": {
        "5kdGZpf1yzFcH4t.png": "dir1"
    },
    "10036": {
        "w6NcLj718Xb5JgA.jpg": "dir1"
    },
    "10048": {
        "9EzyOTrxjB7ndPU.jpg": "dir1"
    },
    "10086": {
        "ra8iWMNn1yXIEjc.jpg": "dir1"
    },
    "10087": {
        "a5JGQ8DK2bjCN7U.jpg": "dir1"
    },
    "10089": {
        "bNuVIrfqXlUPkHZ.jpg": "dir1"
    },
    "10090": {
        "1TgiDZ6fwmzvK7q.jpg": "dir1"
    },
    "10100": {
        "bcE7AVkiN1uxPrn.jpg": "dir1"
    },
    "10136": {
        "k9elus.jpg": "dir1"
    },
    "10154": {
        "0cad25453f48e6d4.jpg": "dir1"
    },
    "10161": {
        "kbdkcw.jpg": "dir1"
    },
    "10178": {
        "8sDewhEnOxqfLQG.jpg": "dir1"
    },
    "10362": {
        "w1ytmn.jpg": "dir1"
    },
    "10404": {
        "lqcabk.jpg": "dir1"
    },
    "10429": {
        "1xe1f3.jpg": "dir1"
    },
    "10442": {
        "1xwwty.jpg": "dir1"
    },
    "10453": {
        "vMiDGswBZWEUyFh.jpg": "dir1"
    },
    "10472": {
        "44eb8aaa9dd5d8a6.jpg": "dir1"
    },
    "10475": {
        "ZHEqheYcMmQs1P9.png": "dir1"
    },
    "10478": {
        "k9gltn.jpg": "dir1"
    },
    "10499": {
        "xvmymw.png": "dir1"
    },
    "10515": {
        "lnzvo1.jpg": "dir1"
    },
    "10528": {
        "2rUYKc6xyZNiTAs.jpg": "dir1"
    },
    "10541": {
        "paOlzfj2vbcg9Ms.jpg": "dir1"
    },
    "10588": {
        "125n6ei.jpg": "dir1"
    },
    "10611": {
        "xu6zeh.jpg": "dir1"
    },
    "10644": {
        "lngmfh.jpg": "dir1"
    },
    "10675": {
        "lr0qpq.jpg": "dir1"
    },
    "10710": {
        "1xt7qj.jpg": "dir1"
    },
    "10720": {
        "B9TjaFxSmYMKzQe.jpg": "dir1"
    },
    "10740": {
        "k9jgpj.jpg": "dir1"
    },
    "10786": {
        "xt7qec.jpg": "dir1"
    },
    "10810": {
        "tYWh3uRdHrUVANX.png": "dir1"
    },
    "10854": {
        "8w4MWPNChKiFjIf.png": "dir1"
    },
    "10857": {
        "lnhma7.jpg": "dir1"
    },
    "10872": {
        "1ya2ab.jpg": "dir1"
    },
    "10886": {
        "wcq13g.jpg": "dir1"
    },
    "10889": {
        "35yHjSBh1xrX7vb.jpg": "dir1"
    },
    "10921": {
        "pPW3mz6ZOJF4DMA.jpg": "dir1"
    },
    "10980": {
        "zFdLoWOJGKPI8X6.jpg": "dir1"
    },
    "10994": {
        "ULTwYvBmyQ5qZ43.jpg": "dir1"
    },
    "11017": {
        "tqiazMZcHrQmfyX.jpg": "dir1"
    },
    "11260": {
        "rbrcyf.jpg": "dir1"
    },
    "11401": {
        "1xy4kl.jpg": "dir1"
    },
    "11413": {
        "lqd148.jpg": "dir1"
    },
    "11421": {
        "9ce71273454e5e73.jpg": "dir1"
    },
    "11516": {
        "ljcnf5.jpg": "dir1"
    },
    "11530": {
        "vHUQ2seloW5hiZ7.jpg": "dir1"
    },
    "11590": {
        "tXeJ7kziTHRO9EP.png": "dir1"
    },
    "11607": {
        "27dce5aed0eedc07.jpg": "dir1",
        "r2hZ5i7wJX1uaS4.jpg": "dir1"
    },
    "11610": {
        "118e688.jpg": "dir1"
    },
    "11640": {
        "k9gta1.jpg": "dir1"
    },
    "11651": {
        "gar96xJIGtwVRKB.jpg": "dir1"
    },
    "11669": {
        "8Wns7X3iuoFwtTI.png": "dir1"
    },
    "11715": {
        "125vpfv.jpg": "dir1"
    },
    "11725": {
        "k92wyz.jpg": "dir1"
    },
    "11742": {
        "TOSkl53QP1zFGea.jpg": "dir1"
    },
    "11747": {
        "w2qf8t.jpg": "dir1"
    },
    "11750": {
        "6423d1c0b1ef22f7.jpg": "dir1",
        "d1EF2MKfQ9Z5Ao6.jpg": "dir1"
    },
    "11771": {
        "lqewez.jpg": "dir1"
    },
    "11773": {
        "UPfB3MokK2Lc9JT.jpg": "dir1"
    },
    "11814": {
        "QTWpvSKZUe2iI4f.jpg": "dir1"
    },
    "11833": {
        "LV91OxyasQpMf3G.jpg": "dir1"
    },
    "11866": {
        "JrdLfIb1ZBkx5wY.jpg": "dir1"
    },
    "11919": {
        "WtbRrUMJn3YSZu6.png": "dir1"
    },
    "11920": {
        "oTGYKuypjrMUZgs.jpg": "dir1"
    },
    "11929": {
        "wd5ifk.jpg": "dir1"
    },
    "11954": {
        "6TnkqWw8CyOdm7J.jpg": "dir1"
    },
    "12143": {
        "rce8e4.jpg": "dir1"
    },
    "12454": {
        "6dbab173fccdfc2f.jpg": "dir1",
        "b0fe8202391feb65.jpg": "dir1"
    },
    "12686": {
        "605ae485d78d144b.jpg": "dir1"
    },
    "13395": {
        "re1mex.jpg": "dir1"
    },
    "13435": {
        "LyAeWfXMZwdHhVi.png": "dir1"
    },
    "13624": {
        "RxEwXzNLs3QCIb6.jpg": "dir1"
    },
    "13636": {
        "ZiIatps754OSmf8.jpg": "dir1"
    },
    "13641": {
        "ZYjgEWal7LikKFu.jpg": "dir1"
    },
    "13676": {
        "p9yvWxeZT6lV7EN.png": "dir1"
    },
    "13754": {
        "83bf058c86505eb0.png": "dir1"
    },
    "13757": {
        "D8PIrUMeFsCGu5n.jpg": "dir1"
    },
    "13779": {
        "eiLOyZxBbVmtvjk.jpg": "dir1"
    },
    "14303": {
        "WDjbCMsyEld4K9k.jpg": "dir1"
    },
    "14318": {
        "bb45b600496f1b34.jpg": "dir1"
    },
    "14468": {
        "91f1c90421ef8741.jpg": "dir1",
        "ad1c1bdcff00e281.jpg": "dir1"
    },
    "14561": {
        "5275215.jpg": "dir1"
    },
    "14576": {
        "Yj57qey32xU1S8a.jpg": "dir1"
    },
    "15404": {
        "dOS6Ai8l9F5f4UQ.jpg": "dir1"
    },
    "15471": {
        "7e69a70b7fbcb55d.jpg": "dir1"
    },
    "15508": {
        "8cBQuvUnbgmyH6N.jpg": "dir1"
    },
    "15533": {
        "45fe10ee9e3ad560.jpeg": "dir1"
    },
    "15839": {
        "U9Rv86HsEGTOwnm.jpg": "dir1"
    },
    "15944": {
        "08f9cce826a087a1.jpg": "dir1"
    },
    "15963": {
        "3b023de426835941.jpg": "dir1"
    },
    "16161": {
        "fa7b1f9d142970df.jpg": "dir1"
    },
    "16215": {
        "b46cb06153c2c85b.jpg": "dir1"
    },
    "16261": {
        "96d2178a0f8298806368ee188442b9_1440w.jpg": "dir2"
    },
    "16380": {
        "MLBUNJAOXf69YzG.jpg": "dir1"
    },
    "16384": {
        "39b351d284567b78.jpg": "dir1"
    },
    "16415": {
        "CcR9Tuva21wOjN4.jpg": "dir1"
    },
    "16416": {
        "baIenMBUECJx6Hh.jpg": "dir1"
    },
    "16462": {
        "fEu4FZUvz5cGNkA.jpg": "dir1"
    },
    "16469": {
        "eGRdcNBW3vyIxmg.jpg": "dir1"
    },
    "16487": {
        "EPFcHedf5w8jUrb.jpg": "dir1"
    },
    "16489": {
        "1OpiXtjZCgYBHLT.jpg": "dir1"
    },
    "16493": {
        "e37ANSGInwdOYgF.jpg": "dir1"
    },
    "16495": {
        "1WjVHC2NAlyS5M4.jpg": "dir1"
    },
    "16498": {
        "CDfEBVstWeuwlYq.jpg": "dir1"
    },
    "16500": {
        "vYaTkuACMzeVXgt.png": "dir1"
    },
    "16538": {
        "1a15997f0acffcca.jpg": "dir1"
    },
    "16539": {
        "5bkImMaUGqrDZvQ.png": "dir1"
    },
    "16555": {
        "nywPlHqi98ZpVmC.jpg": "dir1"
    },
    "16812": {
        "5328329.jpg": "dir1"
    },
    "16877": {
        "5370652.jpg": "dir1"
    },
    "17157": {
        "s4c9PjkFt56NvSy.jpg": "dir2"
    },
    "17262": {
        "P4UCEv1aWLKMneT.jpg": "dir1"
    },
    "17598": {
        "E1a9YnkUefyc62T.jpg": "dir1"
    },
    "17677": {
        "blgIXStcfjz9PRY.jpg": "dir2"
    },
    "17694": {
        "ltbRrDBa3pcNVkj.jpg": "dir2"
    },
    "17787": {
        "dtH4LQ8JCKnvXcG.jpg": "dir2"
    },
    "17796": {
        "23190bbafd954416.jpg": "dir1",
        "c2e66d35f83ed660.jpg": "dir1"
    },
    "17806": {
        "k1YCpsSxFX46Aqw.jpg": "dir2"
    },
    "17849": {
        "3njdk28mORaIsBc.jpg": "dir2"
    },
    "17871": {
        "XZbp37OEQaIVNoA.jpg": "dir2"
    },
    "17893": {
        "oLh3Rf16uxQdkgp.jpg": "dir2"
    },
    "17908": {
        "UI5JPfwNqyljCec.jpg": "dir2"
    },
    "17912": {
        "gOuy7tHqwzWMhrD.jpg": "dir2"
    },
    "17918": {
        "q4s1SjAKBTOu6YG.jpg": "dir2"
    },
    "17923": {
        "Photo-1822938840.jpg": "dir1"
    },
    "17928": {
        "Photo-1822938840.jpg": "dir2"
    },
    "17962": {
        "CNiTWB19Eols5Af.jpg": "dir2"
    },
    "18074": {
        "l1foRAOc8NtDysx.jpg": "dir2"
    },
    "18078": {
        "jzxoy4.jpg": "dir1"
    },
    "18082": {
        "fUylObgtMBhVTQx.jpg": "dir2"
    },
    "18100": {
        "crasLOy3mNJkEUY.png": "dir2"
    },
    "18101": {
        "eWgnFmVQMs64HSO.jpg": "dir1"
    },
    "18104": {
        "6SB8NjJ97LCuiWY.jpg": "dir2"
    },
    "18130": {
        "O5qjIlK43MTYURi.jpg": "dir2"
    },
    "18144": {
        "bFZCVMz24joJ6fA.jpg": "dir2"
    },
    "18148": {
        "Z361nTAaRouU5xC.jpg": "dir2"
    },
    "18197": {
        "Towz9Pc3j1JhxtS.jpg": "dir2"
    },
    "18242": {
        "tx1j1h.jpg": "dir1",
        "tx2esv.gif": "dir1"
    },
    "18274": {
        "H86Ud1AjfkZPGIF.png": "dir2"
    },
    "18309": {
        "UyIevj1lT2w9KqH.png": "dir2"
    },
    "18310": {
        "F4PXktwlVv1mSJT.png": "dir2"
    },
    "18368": {
        "gSYoMRwQ2yJlA71.jpg": "dir1"
    },
    "18378": {
        "iyUHh8uqoIXDVlZ.jpg": "dir1"
    },
    "18385": {
        "xmyPXarVgIh4e6R.jpg": "dir2"
    },
    "18391": {
        "5FpPN2twAgkDZMq.jpg": "dir1"
    },
    "18394": {
        "3FcNVlSyfJ79BR8.jpg": "dir2"
    },
    "18402": {
        "78qt9M1oEwC3yL4.jpg": "dir1"
    },
    "18428": {
        "xDvKj5qmraBNnTs.jpg": "dir2"
    },
    "18500": {
        "206dj00qrq154003kd200j600zeg00j600ze.jpg": "dir1"
    },
    "18579": {
        "OR1XpYWIgczf9uE.jpg": "dir2"
    },
    "18625": {
        "rwA6acs8YmoGgDI.jpg": "dir1"
    },
    "18657": {
        "auSgz8w4bOHW9RA.jpg": "dir1"
    },
    "18668": {
        "MCRpJXzZWUhVfKa.jpg": "dir1"
    },
    "18805": {
        "053db8e233926eb8.jpg": "dir1"
    },
    "18899": {
        "PKUwRAJVm5C7ozQ.jpg": "dir1"
    },
    "18932": {
        "eZszdyRlb7r9K8T.jpg": "dir1"
    },
    "18945": {
        "kLRP9VUwFBSHdJh.jpg": "dir1"
    },
    "18946": {
        "ba2f3c3776fca0b4.jpg": "dir1"
    },
    "18958": {
        "h7DiTpWdJaBQgqX.jpg": "dir1"
    },
    "18969": {
        "x3wkhCJpyO9DN4M.jpg": "dir1"
    },
    "19069": {
        "gGrstxfmA4Ckpda.jpg": "dir2"
    },
    "19098": {
        "GPE9ZrvwjceVWT2.jpg": "dir2"
    },
    "19103": {
        "ca5407d7f3c7aa1f.jpg": "dir1"
    },
    "19130": {
        "0e6b1734fc288337.jpg": "dir1"
    },
    "19243": {
        "ee733bd3df73a5df.jpg": "dir1"
    },
    "19321": {
        "UXxhiTsMHDwECkm.jpg": "dir1"
    },
    "19323": {
        "QRgO65UkqLisc7d.jpg": "dir1"
    },
    "19338": {
        "dK2ptSNraVCH5kZ.jpg": "dir1"
    },
    "19378": {
        "W5ynlzjsFkdiXZO.jpg": "dir2"
    },
    "19399": {
        "z62djBmapEq3gXu.jpg": "dir1"
    },
    "19400": {
        "IfdgtKqMkS3vj6C.jpg": "dir1"
    },
    "19422": {
        "cyts6gYVJmDqeXS.jpg": "dir1"
    },
    "19465": {
        "roYAMXKG2bufBnH.jpg": "dir1"
    },
    "19570": {
        "7XTVlheb2ZqDo4x.jpg": "dir1"
    },
    "19573": {
        "ff3934c6dfbf49b0.jpg": "dir1"
    },
    "19669": {
        "MQSPNlAEmxWR4zg.png": "dir2"
    },
    "19764": {
        "O53vdhjQ1pTeVZB.jpg": "dir2"
    },
    "19767": {
        "9A6fZhwIFNvGK57.jpg": "dir2"
    },
    "19831": {
        "BsDRJStkTlOV2Qx.jpg": "dir1"
    },
    "19861": {
        "b579b907e4312259.jpg": "dir1"
    },
    "19934": {
        "fFgzn3xuSp9WZJC.jpg": "dir1",
        "H7n5aoI3LXKv8fF.jpg": "dir1"
    },
    "20003": {
        "NPfdshwycLQXnFg.png": "dir2"
    },
    "20006": {
        "vsczIHtCYXRyxGu.png": "dir2"
    },
    "20029": {
        "rGfCN8F3KUQBtxn.jpg": "dir2"
    },
    "20049": {
        "WUF4XVxGNQ9RLdS.jpg": "dir2"
    },
    "20060": {
        "31dd9844ab53dfbd.jpg": "dir1"
    },
    "20076": {
        "QsOBjlwIMD8eAUH.jpg": "dir2"
    },
    "20101": {
        "9m8KdwxqiaIXgBY.jpg": "dir2"
    },
    "20120": {
        "Mtq1Ah5K2P4ufXU.jpg": "dir2"
    },
    "20133": {
        "N9EIgzm3YCMySq2.jpg": "dir2"
    },
    "20145": {
        "2LByMuENYQ1rdUI.jpg": "dir2"
    },
    "20149": {
        "OzvDRSAZIykVi2l.jpg": "dir2"
    },
    "20151": {
        "SyXh6qWxzL32srM.jpg": "dir2"
    },
    "20222": {
        "MjdVI7Gwoekg51B.jpg": "dir2"
    },
    "20229": {
        "ec71d4c44eba5af9.jpg": "dir1"
    },
    "20245": {
        "3ShcFfrqinVUwgQ.jpg": "dir2"
    },
    "20385": {
        "R3PDjIs9lbFLAd2.jpg": "dir2"
    },
    "20396": {
        "477ece7b776b69aa.jpg": "dir1"
    },
    "20408": {
        "JTSuKIs3VynUDzN.jpg": "dir2"
    },
    "20411": {
        "RbzKC5pQdNa2v8T.jpg": "dir2"
    },
    "20447": {
        "qLZnkluyv5bpWB6.jpg": "dir2"
    },
    "20466": {
        "JQhZV69Xntz7NfW.jpg": "dir2"
    },
    "20472": {
        "HaG1RBAJhQFDkvZ.png": "dir2",
        "vOpLmPHl3jzr8dQ.png": "dir2"
    },
    "20473": {
        "9a9a20395ae08752.jpg": "dir1"
    },
    "20483": {
        "nB27JsLyH8fv9RK.jpg": "dir2"
    },
    "20484": {
        "wT8eLrQahIGPX6H.jpg": "dir2"
    },
    "20505": {
        "qAHahMkrnVceplK.jpg": "dir2"
    },
    "20548": {
        "YkT1ebmpg7a2JVs.jpg": "dir2"
    },
    "20554": {
        "ytvYFQJ9gs38BdL.jpg": "dir2"
    },
    "20606": {
        "ToRZrdgzp2ynu6A.jpg": "dir1"
    },
    "20636": {
        "8Kc6lu7CFad4VeT.jpg": "dir2"
    },
    "20637": {
        "zmJtHQZBcTa5I2n.jpg": "dir2"
    },
    "20648": {
        "94WFTkJslb56PRe.jpg": "dir2"
    },
    "20693": {
        "LNZfRubBvir8QwT.jpg": "dir2"
    },
    "20701": {
        "IfKvteO9gyqAPSM.jpg": "dir2"
    },
    "20702": {
        "Bj3luNqFyzPfYDw.jpg": "dir2"
    },
    "20746": {
        "5WZM4cIaUERflPL.jpg": "dir2"
    },
    "20784": {
        "VwhmsaZAc93XY7i.jpg": "dir2"
    },
    "20834": {
        "FSoE9Bsn5QgVPrI.jpg": "dir2"
    },
    "20868": {
        "9UnwFBRoYKLagW3.jpg": "dir2"
    },
    "20899": {
        "eIvGRXsgEaWMP4N.png": "dir2"
    },
    "21028": {
        "blkSRH3qvsTXZr4.jpg": "dir2"
    },
    "21050": {
        "AK5TOGdPcNtfIBW.jpg": "dir2"
    },
    "21112": {
        "37ey.jpg": "dir2"
    },
    "21137": {
        "xTkrosqzImXtM6c.jpg": "dir2"
    },
    "21153": {
        "d8e2b765420ca3e7.jpg": "dir1"
    },
    "21374": {
        "999778a7ad0b4907.jpg": "dir1"
    },
    "21608": {
        "dff8d3c1fdadb335.jpg": "dir1"
    },
    "21855": {
        "e295bbaf74930d67.jpg": "dir1"
    },
    "21858": {
        "dc91f99f82158203.jpg": "dir1"
    },
    "22020": {
        "1ff42fc97110bb55.jpg": "dir1",
        "96bc970bcc7e4042.jpg": "dir1"
    },
    "22204": {
        "EGn2cOKDN6Mmpzi.jpg": "dir2"
    },
    "22299": {
        "image.gif": "dir2",
        "image.png": "dir2"
    },
    "22344": {
        "xCGIOZD1P7yvRLK.png": "dir2"
    },
    "22371": {
        "7d21c535faef32fd.jpg": "dir1"
    },
    "22400": {
        "gkazQxiwuYZ3XDy.jpg": "dir2"
    },
    "22460": {
        "77e875ed3dcdc5e8.jpg": "dir1"
    },
    "22504": {
        "7AGJklzIKihOYDN.jpg": "dir2"
    },
    "22606": {
        "WX9pmQ7gdFHK8kS.jpg": "dir2"
    },
    "22638": {
        "BRuKoEP9ilQyM4L.jpg": "dir2"
    },
    "22739": {
        "wxRrhp6TDlYqtV5.jpg": "dir2"
    },
    "22866": {
        "xoIRZPdvFr5Oawc.png": "dir2"
    },
    "22875": {
        "PSBdmbtYU8RyJXh.jpg": "dir2"
    },
    "22886": {
        "jgmRDWqPJKV1ri8.jpg": "dir2"
    },
    "22895": {
        "ozIiW25Nv63AXsH.jpg": "dir2"
    },
    "22896": {
        "AB27ZsYKPHUdDQ8.jpg": "dir2"
    },
    "22898": {
        "gp6FNYSyAa475jZ.jpg": "dir2"
    },
    "23027": {
        "rdzLHTpwOG9PWvb.jpg": "dir2"
    },
    "23036": {
        "lpT7CeVBYOx2d8N.jpg": "dir2"
    },
    "23170": {
        "iD8bHyZQ4ejpSRq.jpg": "dir2"
    },
    "23182": {
        "i4NVaj536EFyT89.jpg": "dir2"
    },
    "23210": {
        "galGVIAj57UuerO.jpg": "dir2"
    },
    "23222": {
        "BSmIKJbzcLuT4PE.jpg": "dir2"
    },
    "23228": {
        "CaLIioOn9x1fr2N.jpg": "dir2"
    },
    "23236": {
        "bFPBJRydKTsMfXA.jpg": "dir2"
    },
    "23301": {
        "oxpIgK7DErH81UY.jpg": "dir2"
    },
    "23309": {
        "fAtiaOVSZ6jF2zP.jpg": "dir2"
    },
    "23363": {
        "qATwxsCEVPHBNy6.jpg": "dir2"
    },
    "23427": {
        "MBPEZwFTopjJNkI.jpg": "dir2"
    },
    "23440": {
        "izOSCylZWbfhJIt.jpg": "dir2"
    },
    "23443": {
        "X45E1WOrFojcMBq.jpg": "dir2"
    },
    "23471": {
        "1DuMXbaoyBprjJ2.jpg": "dir2",
        "61S8aNKc7LZxUfs.jpg": "dir2"
    },
    "23530": {
        "D4GoLO1umtJ89rh.jpg": "dir2"
    },
    "23871": {
        "pstYyoUgFEmjk5H.jpg": "dir1"
    },
    "23902": {
        "zs3mT6HLvxagb7U.jpg": "dir2"
    },
    "23918": {
        "JkXCVgYvAFUSiju.jpg": "dir2"
    },
    "24104": {
        "NqDTPVBpzXZ5xfG.jpg": "dir2",
        "Wz1HAqCrus9JOLE.jpg": "dir1"
    },
    "24212": {
        "MajmFwuY2lcS6Jq.jpg": "dir2"
    },
    "24463": {
        "wdv7p5.png": "dir2"
    },
    "24571": {
        "qLAzgP.jpg": "dir1"
    },
    "24579": {
        "cVIM7Ak9gv54FLj.jpg": "dir2",
        "Jh2UecvXgtmbdGn.jpg": "dir2"
    },
    "24866": {
        "5aziGC4nZHAdMgh.jpg": "dir2",
        "LdNsUOFeq6r1aB9.jpg": "dir2"
    },
    "24970": {
        "7cLMHeP4mquKxpS.jpg": "dir2"
    },
    "24973": {
        "cSseb5Z8g9IMwzU.jpg": "dir2"
    },
    "25007": {
        "lRQtwudaNoW34qL.jpg": "dir2"
    },
    "25154": {
        "qxBPN6.jpg": "dir1"
    },
    "25409": {
        "hfyog.jpg": "dir2"
    },
    "25424": {
        "0220408_082156~jpg~filetype~image~2Fjpeg.jpeg": "dir2"
    },
    "25535": {
        "mN3BcqTet4nW8gL.jpg": "dir2"
    },
    "25662": {
        "b7iloPtZLS8QqFD.jpg": "dir2"
    },
    "25708": {
        "-deb5b8ecc31e2743ce983fd17dde72b3_b.jpeg": "dir2"
    },
    "26283": {
        "~8BDFF2D82536~jpeg~filetype~image~2Fjpeg.jpeg": "dir1"
    },
    "26296": {
        "5jYbrQx7GhvaO8V.png": "dir2"
    },
    "26655": {
        "iCT7rHzGj6hb9nm.png": "dir2"
    },
    "26662": {
        "MOiQHRLTD7jaCd9.jpg": "dir2"
    },
    "26851": {
        "9uwtqDoa7ShvbXG.jpg": "dir2"
    },
    "27081": {
        "8N9ECup6oFe4Btc.png": "dir2"
    },
    "27244": {
        "frvkhKeSRZ6GaAQ.jpg": "dir2",
        "kH59iaZdsjW8POS.jpg": "dir2"
    },
    "27385": {
        "hi2i8d.png": "dir2",
        "hi2t8s.png": "dir2",
        "hi35gz.png": "dir2"
    },
    "27744": {
        "aHWSB48gn7JzDoQ.jpg": "dir2"
    },
    "27772": {
        "8fyY2Q5sLrDbIMp.jpg": "dir2",
        "pUOj4rZeEYBsin5.jpg": "dir2",
        "TX7m3xeNkq9IYW2.jpg": "dir2"
    },
    "27892": {
        "g6h2LsktyXV13AJ.jpg": "dir2"
    },
    "27914": {
        "6co9op.jpg": "dir2"
    },
    "28040": {
        "LJK740.jpg": "dir1"
    },
    "28314": {
        "LtcwAH.jpg": "dir1"
    },
    "28368": {
        "22937373308659~jpg~filetype~image~2Fjpeg.jpeg": "dir1"
    },
    "28516": {
        "fn4YO8rvWjta1Am.png": "dir2",
        "yOT5tlPwv4p3Vkr.png": "dir2"
    },
    "28656": {
        "55~9B5F6A242FA0~png~filetype~image~2Fpng.png": "dir1"
    },
    "28989": {
        "~0073336F2532~jpeg~filetype~image~2Fjpeg.jpeg": "dir1"
    },
    "29111": {
        "MJXDqSCvixjKHAE.png": "dir2"
    },
    "29201": {
        "L05im4.md.png": "dir1",
        "RGCKQpluesP7w9r.png": "dir2"
    },
    "29461": {
        "FBUNORXcgI3fa8Z.jpg": "dir2"
    },
    "29806": {
        "18047a8f90a178413fe2e15f.png!custom.jpg": "dir2"
    },
    "30084": {
        "RUeqaGubKBZVtTc.png": "dir2"
    },
    "30781": {
        "%E8%B5%B5%E7%AB%8B%E5%9D%9A.jpg": "dir2"
    },
    "31125": {
        "LXp2k54y8T3JScH.jpg": "dir2"
    },
    "31561": {
        "p9tpwp.jpg": "dir2"
    },
    "31759": {
        "tfbNUA6BnF5r4WQ.png": "dir2"
    },
    "31854": {
        "lename~~20~46~~jpg~filetype~image~2Fjpeg.jpeg": "dir1"
    },
    "31886": {
        "XN7emtzlVs8juBb.jpg": "dir2"
    },
    "32118": {
        "u8yzub.png": "dir2"
    },
    "32624": {
        "r28CWEH6dtlxhyU.png": "dir2"
    },
    "33192": {
        "FbzJpuwrdnRk1v6.jpg": "dir2"
    },
    "33506": {
        "LzJvM8.jpg": "dir1"
    },
    "33696": {
        "CQTI2t47s3pvqZu.jpg": "dir1"
    },
    "34300": {
        "BLPUobeDR1vmKIN.jpg": "dir1",
        "GTkK8YlgyL54mWq.jpg": "dir1"
    },
    "34912": {
        "~93~88~E5~93~88~PNG~filetype~image~2Fpng.png": "dir1"
    },
    "35847": {
        "hate5l.jpg": "dir1",
        "hatohm.jpg": "dir1",
        "hatoop.jpg": "dir1",
        "hatxru.jpg": "dir1"
    },
    "36705": {
        "szq570.jpeg": "dir1"
    },
    "37493": {
        "DtN5IW3sGEZruHa.jpg": "dir1"
    },
    "37819": {
        "C~96~E5~B7~A5~jpeg~filetype~image~2Fjpeg.jpeg": "dir2"
    },
    "38228": {
        "C1WOs7Q5EYcdaMk.jpg": "dir1"
    },
    "38315": {
        "RVF1NOnahm86pCP.png": "dir1"
    },
    "38407": {
        "879c74f83a728072.jpg": "dir1"
    },
    "39209": {
        "1c3b553fa36c4cd80fd14db66c2acd_1440w.jpg": "dir2"
    }
}